models.py
mosamatic2/__init__.py
mosamatic2/app.py
mosamatic2/cli.py
mosamatic2/commands/__init__.py
mosamatic2/commands/boadockerpipeline.py
mosamatic2/commands/calculatemaskstatistics.py
mosamatic2/commands/calculatescores.py
mosamatic2/commands/createdicomsummary.py
mosamatic2/commands/createpngsfromsegmentations.py
mosamatic2/commands/defaultdockerpipeline.py
mosamatic2/commands/defaultpipeline.py
mosamatic2/commands/dicom2nifti.py
mosamatic2/commands/liveranalysispipeline.py
mosamatic2/commands/rescaledicomimages.py
mosamatic2/commands/segmentmusclefatl3tensorflow.py
mosamatic2/commands/selectslicefromscans.py
mosamatic2/commands/totalsegmentator.py
mosamatic2/constants.py
mosamatic2/core/__init__.py
mosamatic2/core/data/__init__.py
mosamatic2/core/data/dicomimage.py
mosamatic2/core/data/dicomimageseries.py
mosamatic2/core/data/dixonseries.py
mosamatic2/core/data/filedata.py
mosamatic2/core/data/multidicomimage.py
mosamatic2/core/data/multiniftiimage.py
mosamatic2/core/data/multinumpyimage.py
mosamatic2/core/data/niftiimage.py
mosamatic2/core/data/numpyimage.py
mosamatic2/core/managers/__init__.py
mosamatic2/core/managers/logmanager.py
mosamatic2/core/managers/logmanagerlistener.py
mosamatic2/core/pipelines/__init__.py
mosamatic2/core/pipelines/boadockerpipeline/__init__.py
mosamatic2/core/pipelines/boadockerpipeline/boadockerpipeline.py
mosamatic2/core/pipelines/defaultdockerpipeline/__init__.py
mosamatic2/core/pipelines/defaultdockerpipeline/defaultdockerpipeline.py
mosamatic2/core/pipelines/defaultpipeline/__init__.py
mosamatic2/core/pipelines/defaultpipeline/defaultpipeline.py
mosamatic2/core/pipelines/liveranalysispipeline/__init__.py
mosamatic2/core/pipelines/liveranalysispipeline/liveranalysispipeline.py
mosamatic2/core/pipelines/pipeline.py
mosamatic2/core/singleton.py
mosamatic2/core/tasks/__init__.py
mosamatic2/core/tasks/applythresholdtosegmentationstask/__init__.py
mosamatic2-2.0.26.dist-info/entry_points.txt
mosamatic2-2.0.26.dist-info/METADATA
mosamatic2-2.0.26.dist-info/WHEEL
mosamatic2-2.0.26.dist-info/RECORD
