Metadata-Version: 2.3
Name: mosamatic2
Version: 2.0.26
Summary: 
Author: Ralph Brecheisen
Author-email: r.brecheisen@maastrichtuniversity.nl
Requires-Python: >=3.11,<3.12
Classifier: Programming Language :: Python :: 3
Classifier: Programming Language :: Python :: 3.11
Requires-Dist: antspyx (>=0.5.4)
Requires-Dist: dicom2nifti (>=2.6.2)
Requires-Dist: docker (>=7.1.0)
Requires-Dist: flask (>=3.1.2)
Requires-Dist: moosez (>=3.0.29)
Requires-Dist: nibabel (>=5.3.2)
Requires-Dist: numpy (>=1.26.4)
Requires-Dist: openpyxl (>=3.1.5)
Requires-Dist: pandas (>=2.3.2)
Requires-Dist: pendulum (>=3.1.0)
Requires-Dist: pillow (>=11.3.0)
Requires-Dist: pydicom (>=3.0.1)
Requires-Dist: pyqtgraph (>=0.13.7)
Requires-Dist: pyside6-essentials (>=6.9)
Requires-Dist: python-gdcm (>=3.0.26)
Requires-Dist: scipy (>=1.15.3)
Requires-Dist: simpleitk (>=2.5.2)
Requires-Dist: slicer (>=0.0.8)
Requires-Dist: tensorboard (==2.15.2)
Requires-Dist: tensorboard-data-server (==0.7.2)
Requires-Dist: tensorflow (==2.15.*) ; platform_system == "Linux"
Requires-Dist: tensorflow-intel (==2.15.0) ; platform_system == "Windows"
Requires-Dist: tensorflow-io-gcs-filesystem (==0.31.0) ; platform_system == "Windows"
Requires-Dist: tensorflow-io-gcs-filesystem (>=0.31.0) ; platform_system == "Darwin" and platform_machine == "arm64"
Requires-Dist: tensorflow-macos (==2.15.0) ; platform_system == "Darwin" and platform_machine == "arm64"
Requires-Dist: torch (==2.5.1)
Requires-Dist: torchsummary
Requires-Dist: torchvision (>=0.20.1)
Requires-Dist: totalsegmentator (>=2.11.0)
Requires-Dist: vtk (>=9.5.1)
Requires-Dist: webdavclient3 (>=3.14.6)
